pyswmm/__init__.py
pyswmm/_monkey_patch.py
pyswmm/config.py
pyswmm/errors.py
pyswmm/lidcontrols.py
pyswmm/lidgroups.py
pyswmm/lidlayers.py
pyswmm/lidunits.py
pyswmm/links.py
pyswmm/nodes.py
pyswmm/output.py
pyswmm/raingages.py
pyswmm/reader.py
pyswmm/simulation.py
pyswmm/subcatchments.py
pyswmm/swmm5.py
pyswmm/system.py
pyswmm/toolkitapi.py
pyswmm/tests/__init__.py
pyswmm/tests/test_current_time.py
pyswmm/tests/test_errors.py
pyswmm/tests/test_general_engine.py
pyswmm/tests/test_lid.py
pyswmm/tests/test_links.py
pyswmm/tests/test_nodes.py
pyswmm/tests/test_output.py
pyswmm/tests/test_pollutants.py
pyswmm/tests/test_rainfallAPI.py
pyswmm/tests/test_simulation.py
pyswmm/tests/test_subcatchments.py
pyswmm/tests/test_system.py
pyswmm/tests/data/__init__.py
pyswmm/tests/data/model_bad_input_1.inp
pyswmm/tests/data/model_constantinflow_constanteffluent.inp
pyswmm/tests/data/model_full_features.inp
pyswmm/tests/data/model_lids.inp
pyswmm/tests/data/model_node_inflows.inp
pyswmm/tests/data/model_pollutants.inp
pyswmm/tests/data/model_pollutants_2.inp
pyswmm/tests/data/model_pollutants_setters.inp
pyswmm/tests/data/model_pump_setting.inp
pyswmm/tests/data/model_rain.inp
pyswmm/tests/data/model_storage_pump.inp
pyswmm/tests/data/model_storage_pump_MGD.inp
pyswmm/tests/data/model_subcatch_stats.inp
pyswmm/tests/data/model_toolkit_units.inp
pyswmm/tests/data/model_weir_setting.inp
pyswmm/tests/data/model_weir_setting_a.inp
pyswmm/utils/__init__.py
pyswmm/utils/fixtures.py
pyswmm-2.0.0.dist-info/AUTHORS
pyswmm-2.0.0.dist-info/LICENSE.txt
pyswmm-2.0.0.dist-info/METADATA
pyswmm-2.0.0.dist-info/WHEEL
pyswmm-2.0.0.dist-info/top_level.txt
pyswmm-2.0.0.dist-info/RECORD
