Metadata-Version: 2.1
Name: pyswmm
Version: 2.0.0
Summary: Python Wrapper for SWMM5 API
Home-page: https://www.pyswmm.org
Author: Bryant E. McDonnell (See AUTHORS)
License: BSD2 License
Keywords: swmm5,swmm,hydraulics,hydrology,modeling,collection system
Classifier: Topic :: Scientific/Engineering
Classifier: Topic :: Documentation :: Sphinx
Classifier: Operating System :: Microsoft :: Windows
Classifier: Operating System :: Unix
Classifier: Operating System :: MacOS
Classifier: License :: OSI Approved :: BSD License
Classifier: Programming Language :: Python :: 3.7
Classifier: Programming Language :: Python :: 3.8
Classifier: Programming Language :: Python :: 3.9
Classifier: Programming Language :: Python :: 3.10
Classifier: Programming Language :: Python :: 3.11
Classifier: Programming Language :: Python :: 3.12
Classifier: Programming Language :: Python
Classifier: Development Status :: 5 - Production/Stable
License-File: LICENSE.txt
License-File: AUTHORS
Requires-Dist: swmm-toolkit >=0.9.0
Requires-Dist: julian >=0.14
Requires-Dist: aenum >=3.1.11
Requires-Dist: packaging
Provides-Extra: swmm5.1.14
Requires-Dist: swmm-toolkit ==0.9.1 ; extra == 'swmm5.1.14'
Provides-Extra: swmm5.1.15
Requires-Dist: swmm-toolkit ==0.10.0 ; extra == 'swmm5.1.15'
Provides-Extra: swmm5.2.0
Requires-Dist: swmm-toolkit ==0.11.0 ; extra == 'swmm5.2.0'
Provides-Extra: swmm5.2.1
Requires-Dist: swmm-toolkit ==0.12.0 ; extra == 'swmm5.2.1'
Provides-Extra: swmm5.2.2
Requires-Dist: swmm-toolkit ==0.13.0 ; extra == 'swmm5.2.2'
Provides-Extra: swmm5.2.3
Requires-Dist: swmm-toolkit ==0.14.0 ; extra == 'swmm5.2.3'
Provides-Extra: swmm5.2.4
Requires-Dist: swmm-toolkit ==0.15.3 ; extra == 'swmm5.2.4'
